{
  "tabPane": [
    {
      "title": "SmartDashboard",
      "autoPopulate": false,
      "autoPopulatePrefix": "SmartDashboard/",
      "widgetPane": {
        "gridSize": 128.0,
        "showGrid": true,
        "hgap": 16.0,
        "vgap": 16.0,
        "titleType": 0,
        "tiles": {
          "3,0": {
            "size": [
              2,
              6
            ],
            "content": {
              "_type": "List Layout",
              "_title": "Shooter",
              "Layout/Label position": "LEFT",
              "_children": [
                {
                  "_type": "Text View",
                  "_source0": "network_table:///SmartDashboard/Shooter Position Rev",
                  "_title": "Shooter Position Rev"
                },
                {
                  "_type": "Text View",
                  "_source0": "network_table:///SmartDashboard/Shooter Velocity RPM",
                  "_title": "Shooter Velocity RPM"
                },
                {
                  "_type": "Command",
                  "_source0": "network_table:///SmartDashboard/Shooter Stop",
                  "_title": "Shooter Stop"
                },
                {
                  "_type": "Text View",
                  "_source0": "network_table:///SmartDashboard/Shooter Percent",
                  "_title": "Shooter Percent"
                },
                {
                  "_type": "Command",
                  "_source0": "network_table:///SmartDashboard/Shooter Set Percent",
                  "_title": "Shooter Set Percent"
                },
                {
                  "_type": "Text View",
                  "_source0": "network_table:///SmartDashboard/Shooter P",
                  "_title": "Shooter P"
                },
                {
                  "_type": "Text View",
                  "_source0": "network_table:///SmartDashboard/Shooter I",
                  "_title": "Shooter I"
                },
                {
                  "_type": "Text View",
                  "_source0": "network_table:///SmartDashboard/Shooter D",
                  "_title": "Shooter D"
                },
                {
                  "_type": "Text View",
                  "_source0": "network_table:///SmartDashboard/Shooter S",
                  "_title": "Shooter S"
                },
                {
                  "_type": "Text View",
                  "_source0": "network_table:///SmartDashboard/Shooter V",
                  "_title": "Shooter V"
                },
                {
                  "_type": "Command",
                  "_source0": "network_table:///SmartDashboard/Shooter Set PID",
                  "_title": "Shooter Set PID"
                },
                {
                  "_type": "Text View",
                  "_source0": "network_table:///SmartDashboard/Shooter SetPoint RPM",
                  "_title": "Shooter SetPoint RPM"
                },
                {
                  "_type": "Command",
                  "_source0": "network_table:///SmartDashboard/Shooter Set Velocity",
                  "_title": "Shooter Set Velocity"
                },
                {
                  "_type": "Text View",
                  "_source0": "network_table:///SmartDashboard/Shooter Voltage",
                  "_title": "Shooter Voltage"
                },
                {
                  "_type": "Text View",
                  "_source0": "network_table:///SmartDashboard/Shooter Temperature C",
                  "_title": "Shooter Temperature C"
                },
                {
                  "_type": "Command",
                  "_source0": "network_table:///SmartDashboard/Shooter Calibrate Fwd",
                  "_title": "Shooter Calibrate Fwd"
                },
                {
                  "_type": "Text View",
                  "_source0": "network_table:///SmartDashboard/Shooter Distance Feet",
                  "_title": "Shooter Distance Feet"
                },
                {
                  "_type": "Command",
                  "_source0": "network_table:///SmartDashboard/Shooter Distance to RPM",
                  "_title": "Shooter Distance to RPM"
                },
                {
                  "_type": "Text View",
                  "_source0": "network_table:///SmartDashboard/Shooter RPM from Dist",
                  "_title": "Shooter RPM from Dist"
                }
              ]
            }
          },
          "5,0": {
            "size": [
              2,
              5
            ],
            "content": {
              "_type": "List Layout",
              "_title": "Feeder",
              "Layout/Label position": "LEFT",
              "_children": [
                {
                  "_type": "Boolean Box",
                  "_source0": "network_table:///SmartDashboard/Feeder Is Ball Present",
                  "_title": "Feeder Is Ball Present",
                  "Colors/Color when true": "#7CFC00FF",
                  "Colors/Color when false": "#8B0000FF"
                },
                {
                  "_type": "Boolean Box",
                  "_source0": "network_table:///SmartDashboard/Eject Ball Present",
                  "_title": "Eject Ball Present",
                  "Colors/Color when true": "#7CFC00FF",
                  "Colors/Color when false": "#8B0000FF"
                },
                {
                  "_type": "Command",
                  "_source0": "network_table:///SmartDashboard/Stop Feeder",
                  "_title": "Stop Feeder"
                },
                {
                  "_type": "Text View",
                  "_source0": "network_table:///SmartDashboard/Feeder Percent",
                  "_title": "Feeder Percent"
                },
                {
                  "_type": "Command",
                  "_source0": "network_table:///SmartDashboard/Set Feeder Percent",
                  "_title": "Set Feeder Percent"
                },
                {
                  "_type": "Text View",
                  "_source0": "network_table:///SmartDashboard/Feeder Voltage",
                  "_title": "Feeder Voltage"
                },
                {
                  "_type": "Command",
                  "_source0": "network_table:///SmartDashboard/Start Feeder Sequence",
                  "_title": "Start Feeder Sequence"
                },
                {
                  "_type": "Command",
                  "_source0": "network_table:///SmartDashboard/Start Shooter Sequence",
                  "_title": "Start Shooter Sequence"
                }
              ]
            }
          },
          "1,0": {
            "size": [
              1,
              1
            ],
            "content": {
              "_type": "Text View",
              "_source0": "network_table:///SmartDashboard/limelight_PipelineName",
              "_title": "limelight_PipelineName"
            }
          },
          "2,0": {
            "size": [
              1,
              1
            ],
            "content": {
              "_type": "Text View",
              "_source0": "network_table:///SmartDashboard/limelight_Interface",
              "_title": "limelight_Interface"
            }
          },
          "0,0": {
            "size": [
              1,
              1
            ],
            "content": {
              "_type": "Text View",
              "_source0": "network_table:///SmartDashboard/limelight_Stream",
              "_title": "limelight_Stream"
            }
          },
          "7,0": {
            "size": [
              2,
              5
            ],
            "content": {
              "_type": "List Layout",
              "_title": "Uptake",
              "Layout/Label position": "LEFT",
              "_children": [
                {
                  "_type": "Text View",
                  "_source0": "network_table:///SmartDashboard/Uptake Uptake Position Rev",
                  "_title": "Uptake Uptake Position Rev"
                },
                {
                  "_type": "Text View",
                  "_source0": "network_table:///SmartDashboard/Uptake Eject Position Rev",
                  "_title": "Uptake Eject Position Rev"
                },
                {
                  "_type": "Text View",
                  "_source0": "network_table:///SmartDashboard/Uptake Uptake Velocity RPM",
                  "_title": "Uptake Uptake Velocity RPM"
                },
                {
                  "_type": "Text View",
                  "_source0": "network_table:///SmartDashboard/Uptake Eject Velocity RPM",
                  "_title": "Uptake Eject Velocity RPM"
                },
                {
                  "_type": "Command",
                  "_source0": "network_table:///SmartDashboard/Uptake Stop",
                  "_title": "Uptake Stop"
                },
                {
                  "_type": "Text View",
                  "_source0": "network_table:///SmartDashboard/Uptake Uptake Voltage",
                  "_title": "Uptake Uptake Voltage"
                },
                {
                  "_type": "Text View",
                  "_source0": "network_table:///SmartDashboard/Uptake Eject Voltage",
                  "_title": "Uptake Eject Voltage"
                },
                {
                  "_type": "Text View",
                  "_source0": "network_table:///SmartDashboard/Uptake Uptake Temperature C",
                  "_title": "Uptake Uptake Temperature C"
                },
                {
                  "_type": "Text View",
                  "_source0": "network_table:///SmartDashboard/Uptake Eject Temperature C",
                  "_title": "Uptake Eject Temperature C"
                },
                {
                  "_type": "Command",
                  "_source0": "network_table:///SmartDashboard/Uptake Run Upward",
                  "_title": "Uptake Run Upward"
                },
                {
                  "_type": "Command",
                  "_source0": "network_table:///SmartDashboard/Uptake Eject Ball",
                  "_title": "Uptake Eject Ball"
                },
                {
                  "_type": "Text View",
                  "_source0": "network_table:///SmartDashboard/Color Proximity",
                  "_title": "Color Proximity"
                },
                {
                  "_type": "Text View",
                  "_source0": "network_table:///SmartDashboard/Color Red",
                  "_title": "Color Red"
                },
                {
                  "_type": "Text View",
                  "_source0": "network_table:///SmartDashboard/Color Green",
                  "_title": "Color Green"
                },
                {
                  "_type": "Text View",
                  "_source0": "network_table:///SmartDashboard/Color Blue",
                  "_title": "Color Blue"
                },
                {
                  "_type": "Text View",
                  "_source0": "network_table:///SmartDashboard/Color",
                  "_title": "Color"
                }
              ]
            }
          },
          "9,0": {
            "size": [
              2,
              6
            ],
            "content": {
              "_type": "List Layout",
              "_title": "Turret",
              "Layout/Label position": "LEFT",
              "_children": [
                {
                  "_type": "Boolean Box",
                  "_source0": "network_table:///SmartDashboard/Turret isCalibrated",
                  "_title": "Turret isCalibrated",
                  "Colors/Color when true": "#7CFC00FF",
                  "Colors/Color when false": "#8B0000FF"
                },
                {
                  "_type": "Text View",
                  "_source0": "network_table:///SmartDashboard/Turret Position Deg",
                  "_title": "Turret Position Deg"
                },
                {
                  "_type": "Text View",
                  "_source0": "network_table:///SmartDashboard/Turret Velocity DegPerSec",
                  "_title": "Turret Velocity DegPerSec"
                },
                {
                  "_type": "Command",
                  "_source0": "network_table:///SmartDashboard/Turret Stop",
                  "_title": "Turret Stop"
                },
                {
                  "_type": "Text View",
                  "_source0": "network_table:///SmartDashboard/Turret Percent",
                  "_title": "Turret Percent"
                },
                {
                  "_type": "Command",
                  "_source0": "network_table:///SmartDashboard/Turret Set Percent",
                  "_title": "Turret Set Percent"
                },
                {
                  "_type": "Boolean Box",
                  "_source0": "network_table:///SmartDashboard/Turret Fwd Limit",
                  "_title": "Turret Fwd Limit",
                  "Colors/Color when true": "#7CFC00FF",
                  "Colors/Color when false": "#8B0000FF"
                },
                {
                  "_type": "Boolean Box",
                  "_source0": "network_table:///SmartDashboard/Turret Rev Limit",
                  "_title": "Turret Rev Limit",
                  "Colors/Color when true": "#7CFC00FF",
                  "Colors/Color when false": "#8B0000FF"
                },
                {
                  "_type": "Boolean Box",
                  "_source0": "network_table:///SmartDashboard/Turret Cal Switch",
                  "_title": "Turret Cal Switch",
                  "Colors/Color when true": "#7CFC00FF",
                  "Colors/Color when false": "#8B0000FF"
                },
                {
                  "_type": "Text View",
                  "_source0": "network_table:///SmartDashboard/Turret Voltage",
                  "_title": "Turret Voltage"
                },
                {
                  "_type": "Text View",
                  "_source0": "network_table:///SmartDashboard/Turret Temperature C",
                  "_title": "Turret Temperature C"
                },
                {
                  "_type": "Command",
                  "_source0": "network_table:///SmartDashboard/Turret Calibrate Fwd",
                  "_title": "Turret Calibrate Fwd"
                },
                {
                  "_type": "Text View",
                  "_source0": "network_table:///SmartDashboard/TurnTurret Manual Target Ang",
                  "_title": "TurnTurret Manual Target Ang"
                },
                {
                  "_type": "Command",
                  "_source0": "network_table:///SmartDashboard/Turret Turn to Angle",
                  "_title": "Turret Turn to Angle"
                },
                {
                  "_type": "Text View",
                  "_source0": "network_table:///SmartDashboard/TurnTurret Manual MaxVel",
                  "_title": "TurnTurret Manual MaxVel"
                },
                {
                  "_type": "Text View",
                  "_source0": "network_table:///SmartDashboard/TurnTurret Manual MaxAccel",
                  "_title": "TurnTurret Manual MaxAccel"
                },
                {
                  "_type": "Text View",
                  "_source0": "network_table:///SmartDashboard/TurnTurret Manual Tolerance",
                  "_title": "TurnTurret Manual Tolerance"
                }
              ]
            }
          },
          "11,0": {
            "size": [
              2,
              4
            ],
            "content": {
              "_type": "List Layout",
              "_title": "Intake",
              "Layout/Label position": "LEFT",
              "_children": [
                {
                  "_type": "Command",
                  "_source0": "network_table:///SmartDashboard/Intake Front Stop",
                  "_title": "Intake Front Stop"
                },
                {
                  "_type": "Command",
                  "_source0": "network_table:///SmartDashboard/Intake Front Fwd",
                  "_title": "Intake Front Fwd"
                },
                {
                  "_type": "Command",
                  "_source0": "network_table:///SmartDashboard/Intake Front Rev",
                  "_title": "Intake Front Rev"
                },
                {
                  "_type": "Text View",
                  "_source0": "network_table:///SmartDashboard/Intake-Front Voltage",
                  "_title": "Intake-Front Voltage"
                },
                {
                  "_type": "Text View",
                  "_source0": "network_table:///SmartDashboard/Intake-Front Transfer Voltage",
                  "_title": "Intake-Front Transfer Voltage"
                },
                {
                  "_type": "Text View",
                  "_source0": "network_table:///SmartDashboard/Intake-Front Position Rev",
                  "_title": "Intake-Front Position Rev"
                },
                {
                  "_type": "Text View",
                  "_source0": "network_table:///SmartDashboard/Intake-Front Velocity RPM",
                  "_title": "Intake-Front Velocity RPM"
                },
                {
                  "_type": "Text View",
                  "_source0": "network_table:///SmartDashboard/Intake-Front Temperature C",
                  "_title": "Intake-Front Temperature C"
                },
                {
                  "_type": "Text View",
                  "_source0": "network_table:///SmartDashboard/Intake-Front Transfer Temperature C",
                  "_title": "Intake-Front Transfer Temperature C"
                }
              ]
            }
          }
        }
      }
    },
    {
      "title": "LiveWindow",
      "autoPopulate": true,
      "autoPopulatePrefix": "LiveWindow/",
      "widgetPane": {
        "gridSize": 128.0,
        "showGrid": true,
        "hgap": 16.0,
        "vgap": 16.0,
        "titleType": 0,
        "tiles": {
          "6,0": {
            "size": [
              2,
              4
            ],
            "content": {
              "_type": "Subsystem Layout",
              "_source0": "network_table:///LiveWindow/Feeder",
              "_title": "Feeder",
              "Layout/Label position": "BOTTOM",
              "_children": []
            }
          },
          "8,0": {
            "size": [
              2,
              4
            ],
            "content": {
              "_type": "Subsystem Layout",
              "_source0": "network_table:///LiveWindow/Shooter",
              "_title": "Shooter",
              "Layout/Label position": "BOTTOM",
              "_children": []
            }
          },
          "10,0": {
            "size": [
              2,
              4
            ],
            "content": {
              "_type": "Subsystem Layout",
              "_source0": "network_table:///LiveWindow/Uptake",
              "_title": "Uptake",
              "Layout/Label position": "BOTTOM",
              "_children": []
            }
          },
          "0,0": {
            "size": [
              1,
              2
            ],
            "content": {
              "_type": "PID Controller",
              "_source0": "network_table:///LiveWindow/Ungrouped/PIDController[3]",
              "_title": "Ungrouped/PIDController[3]"
            }
          },
          "1,0": {
            "size": [
              2,
              4
            ],
            "content": {
              "_type": "Subsystem Layout",
              "_source0": "network_table:///LiveWindow/DriveTrain",
              "_title": "DriveTrain",
              "Layout/Label position": "BOTTOM",
              "_children": []
            }
          },
          "3,0": {
            "size": [
              2,
              1
            ],
            "content": {
              "_type": "Motor Controller",
              "_source0": "network_table:///LiveWindow/Ungrouped/Talon FX [12]",
              "_title": "Ungrouped/Talon FX [12]",
              "Visuals/Orientation": "HORIZONTAL"
            }
          },
          "3,1": {
            "size": [
              2,
              2
            ],
            "content": {
              "_type": "Gyro",
              "_source0": "network_table:///LiveWindow/Ungrouped/navX-Sensor[2]",
              "_title": "Ungrouped/navX-Sensor[2]",
              "Visuals/Major tick spacing": 45.0,
              "Visuals/Starting angle": 180.0,
              "Visuals/Show tick mark ring": true,
              "Visuals/Counter clockwise": false
            }
          },
          "5,0": {
            "size": [
              1,
              2
            ],
            "content": {
              "_type": "PID Controller",
              "_source0": "network_table:///LiveWindow/Ungrouped/PIDController[7]",
              "_title": "Ungrouped/PIDController[7]"
            }
          },
          "12,0": {
            "size": [
              1,
              2
            ],
            "content": {
              "_type": "PID Controller",
              "_source0": "network_table:///LiveWindow/Ungrouped/PIDController[8]",
              "_title": "Ungrouped/PIDController[8]"
            }
          },
          "0,2": {
            "size": [
              1,
              1
            ],
            "content": {
              "_type": "Boolean Box",
              "_source0": "network_table:///LiveWindow/Ungrouped/DigitalInput[1]/Value",
              "_title": "Ungrouped/DigitalInput[1]/Value",
              "Colors/Color when true": "#7CFC00FF",
              "Colors/Color when false": "#8B0000FF"
            }
          },
          "5,2": {
            "size": [
              1,
              2
            ],
            "content": {
              "_type": "PID Controller",
              "_source0": "network_table:///LiveWindow/Ungrouped/PIDController[11]",
              "_title": "Ungrouped/PIDController[11]"
            }
          },
          "12,2": {
            "size": [
              1,
              2
            ],
            "content": {
              "_type": "PID Controller",
              "_source0": "network_table:///LiveWindow/Ungrouped/PIDController[10]",
              "_title": "Ungrouped/PIDController[10]"
            }
          },
          "3,3": {
            "size": [
              2,
              1
            ],
            "content": {
              "_type": "Motor Controller",
              "_source0": "network_table:///LiveWindow/Ungrouped/Talon FX [34]",
              "_title": "Ungrouped/Talon FX [34]",
              "Visuals/Orientation": "HORIZONTAL"
            }
          },
          "0,4": {
            "size": [
              2,
              1
            ],
            "content": {
              "_type": "Motor Controller",
              "_source0": "network_table:///LiveWindow/Ungrouped/Talon FX [16]",
              "_title": "Ungrouped/Talon FX [16]",
              "Visuals/Orientation": "HORIZONTAL"
            }
          },
          "0,3": {
            "size": [
              1,
              1
            ],
            "content": {
              "_type": "Boolean Box",
              "_source0": "network_table:///LiveWindow/Ungrouped/DigitalInput[2]/Value",
              "_title": "Ungrouped/DigitalInput[2]/Value",
              "Colors/Color when true": "#7CFC00FF",
              "Colors/Color when false": "#8B0000FF"
            }
          },
          "2,4": {
            "size": [
              1,
              2
            ],
            "content": {
              "_type": "PID Controller",
              "_source0": "network_table:///LiveWindow/Ungrouped/PIDController[9]",
              "_title": "Ungrouped/PIDController[9]"
            }
          },
          "3,4": {
            "size": [
              1,
              2
            ],
            "content": {
              "_type": "PID Controller",
              "_source0": "network_table:///LiveWindow/Ungrouped/PIDController[1]",
              "_title": "Ungrouped/PIDController[1]"
            }
          },
          "4,4": {
            "size": [
              2,
              1
            ],
            "content": {
              "_type": "Motor Controller",
              "_source0": "network_table:///LiveWindow/Ungrouped/Talon FX [31]",
              "_title": "Ungrouped/Talon FX [31]",
              "Visuals/Orientation": "HORIZONTAL"
            }
          },
          "6,4": {
            "size": [
              2,
              1
            ],
            "content": {
              "_type": "Motor Controller",
              "_source0": "network_table:///LiveWindow/Ungrouped/Talon FX [22]",
              "_title": "Ungrouped/Talon FX [22]",
              "Visuals/Orientation": "HORIZONTAL"
            }
          },
          "8,4": {
            "size": [
              1,
              2
            ],
            "content": {
              "_type": "PID Controller",
              "_source0": "network_table:///LiveWindow/Ungrouped/PIDController[4]",
              "_title": "Ungrouped/PIDController[4]"
            }
          },
          "9,4": {
            "size": [
              1,
              2
            ],
            "content": {
              "_type": "PID Controller",
              "_source0": "network_table:///LiveWindow/Ungrouped/PIDController[2]",
              "_title": "Ungrouped/PIDController[2]"
            }
          },
          "10,4": {
            "size": [
              2,
              1
            ],
            "content": {
              "_type": "Motor Controller",
              "_source0": "network_table:///LiveWindow/Ungrouped/Talon FX [21]",
              "_title": "Ungrouped/Talon FX [21]",
              "Visuals/Orientation": "HORIZONTAL"
            }
          },
          "0,5": {
            "size": [
              2,
              1
            ],
            "content": {
              "_type": "Motor Controller",
              "_source0": "network_table:///LiveWindow/Ungrouped/Talon FX [33]",
              "_title": "Ungrouped/Talon FX [33]",
              "Visuals/Orientation": "HORIZONTAL"
            }
          },
          "12,4": {
            "size": [
              1,
              2
            ],
            "content": {
              "_type": "PID Controller",
              "_source0": "network_table:///LiveWindow/Ungrouped/PIDController[6]",
              "_title": "Ungrouped/PIDController[6]"
            }
          },
          "4,5": {
            "size": [
              2,
              1
            ],
            "content": {
              "_type": "Motor Controller",
              "_source0": "network_table:///LiveWindow/Ungrouped/Talon FX [35]",
              "_title": "Ungrouped/Talon FX [35]",
              "Visuals/Orientation": "HORIZONTAL"
            }
          },
          "6,5": {
            "size": [
              1,
              1
            ],
            "content": {
              "_type": "Text View",
              "_source0": "network_table:///LiveWindow/Ungrouped/DifferentialDrive[1]/Left Motor Speed",
              "_title": "Ungrouped/DifferentialDrive[1]/Left Motor Speed"
            }
          },
          "7,5": {
            "size": [
              1,
              1
            ],
            "content": {
              "_type": "Text View",
              "_source0": "network_table:///LiveWindow/Ungrouped/DifferentialDrive[1]/Right Motor Speed",
              "_title": "Ungrouped/DifferentialDrive[1]/Right Motor Speed"
            }
          },
          "10,5": {
            "size": [
              2,
              1
            ],
            "content": {
              "_type": "Motor Controller",
              "_source0": "network_table:///LiveWindow/Ungrouped/Talon FX [32]",
              "_title": "Ungrouped/Talon FX [32]",
              "Visuals/Orientation": "HORIZONTAL"
            }
          },
          "0,6": {
            "size": [
              2,
              1
            ],
            "content": {
              "_type": "Motor Controller",
              "_source0": "network_table:///LiveWindow/Ungrouped/Talon FX [19]",
              "_title": "Ungrouped/Talon FX [19]",
              "Visuals/Orientation": "HORIZONTAL"
            }
          },
          "2,6": {
            "size": [
              1,
              1
            ],
            "content": {
              "_type": "Boolean Box",
              "_source0": "network_table:///LiveWindow/Ungrouped/DigitalInput[3]/Value",
              "_title": "Ungrouped/DigitalInput[3]/Value",
              "Colors/Color when true": "#7CFC00FF",
              "Colors/Color when false": "#8B0000FF"
            }
          },
          "3,6": {
            "size": [
              2,
              1
            ],
            "content": {
              "_type": "Motor Controller",
              "_source0": "network_table:///LiveWindow/Ungrouped/Talon FX [36]",
              "_title": "Ungrouped/Talon FX [36]",
              "Visuals/Orientation": "HORIZONTAL"
            }
          },
          "5,6": {
            "size": [
              1,
              1
            ],
            "content": {
              "_type": "Boolean Box",
              "_source0": "network_table:///LiveWindow/Ungrouped/Compressor[1]/Enabled",
              "_title": "Ungrouped/Compressor[1]/Enabled",
              "Colors/Color when true": "#7CFC00FF",
              "Colors/Color when false": "#8B0000FF"
            }
          },
          "6,6": {
            "size": [
              1,
              1
            ],
            "content": {
              "_type": "Boolean Box",
              "_source0": "network_table:///LiveWindow/Ungrouped/Compressor[1]/Pressure switch",
              "_title": "Ungrouped/Compressor[1]/Pressure switch",
              "Colors/Color when true": "#7CFC00FF",
              "Colors/Color when false": "#8B0000FF"
            }
          },
          "7,6": {
            "size": [
              1,
              1
            ],
            "content": {
              "_type": "Text View",
              "_source0": "network_table:///LiveWindow/Ungrouped/PowerDistribution[1]/Chan0",
              "_title": "Ungrouped/PowerDistribution[1]/Chan0"
            }
          },
          "8,6": {
            "size": [
              1,
              1
            ],
            "content": {
              "_type": "Text View",
              "_source0": "network_table:///LiveWindow/Ungrouped/PowerDistribution[1]/Chan1",
              "_title": "Ungrouped/PowerDistribution[1]/Chan1"
            }
          },
          "9,6": {
            "size": [
              1,
              1
            ],
            "content": {
              "_type": "Text View",
              "_source0": "network_table:///LiveWindow/Ungrouped/PowerDistribution[1]/Chan2",
              "_title": "Ungrouped/PowerDistribution[1]/Chan2"
            }
          },
          "10,6": {
            "size": [
              1,
              1
            ],
            "content": {
              "_type": "Text View",
              "_source0": "network_table:///LiveWindow/Ungrouped/PowerDistribution[1]/Chan3",
              "_title": "Ungrouped/PowerDistribution[1]/Chan3"
            }
          },
          "11,6": {
            "size": [
              1,
              1
            ],
            "content": {
              "_type": "Text View",
              "_source0": "network_table:///LiveWindow/Ungrouped/PowerDistribution[1]/Chan4",
              "_title": "Ungrouped/PowerDistribution[1]/Chan4"
            }
          },
          "12,6": {
            "size": [
              1,
              1
            ],
            "content": {
              "_type": "Text View",
              "_source0": "network_table:///LiveWindow/Ungrouped/PowerDistribution[1]/Chan5",
              "_title": "Ungrouped/PowerDistribution[1]/Chan5"
            }
          },
          "0,7": {
            "size": [
              1,
              1
            ],
            "content": {
              "_type": "Text View",
              "_source0": "network_table:///LiveWindow/Ungrouped/PowerDistribution[1]/Chan6",
              "_title": "Ungrouped/PowerDistribution[1]/Chan6"
            }
          },
          "1,7": {
            "size": [
              1,
              1
            ],
            "content": {
              "_type": "Text View",
              "_source0": "network_table:///LiveWindow/Ungrouped/PowerDistribution[1]/Chan7",
              "_title": "Ungrouped/PowerDistribution[1]/Chan7"
            }
          },
          "2,7": {
            "size": [
              1,
              1
            ],
            "content": {
              "_type": "Text View",
              "_source0": "network_table:///LiveWindow/Ungrouped/PowerDistribution[1]/Chan8",
              "_title": "Ungrouped/PowerDistribution[1]/Chan8"
            }
          },
          "3,7": {
            "size": [
              1,
              1
            ],
            "content": {
              "_type": "Text View",
              "_source0": "network_table:///LiveWindow/Ungrouped/PowerDistribution[1]/Chan9",
              "_title": "Ungrouped/PowerDistribution[1]/Chan9"
            }
          },
          "4,7": {
            "size": [
              1,
              1
            ],
            "content": {
              "_type": "Text View",
              "_source0": "network_table:///LiveWindow/Ungrouped/PowerDistribution[1]/Chan10",
              "_title": "Ungrouped/PowerDistribution[1]/Chan10"
            }
          },
          "5,7": {
            "size": [
              1,
              1
            ],
            "content": {
              "_type": "Text View",
              "_source0": "network_table:///LiveWindow/Ungrouped/PowerDistribution[1]/Chan11",
              "_title": "Ungrouped/PowerDistribution[1]/Chan11"
            }
          },
          "6,7": {
            "size": [
              1,
              1
            ],
            "content": {
              "_type": "Text View",
              "_source0": "network_table:///LiveWindow/Ungrouped/PowerDistribution[1]/Chan12",
              "_title": "Ungrouped/PowerDistribution[1]/Chan12"
            }
          },
          "7,7": {
            "size": [
              1,
              1
            ],
            "content": {
              "_type": "Text View",
              "_source0": "network_table:///LiveWindow/Ungrouped/PowerDistribution[1]/Chan13",
              "_title": "Ungrouped/PowerDistribution[1]/Chan13"
            }
          },
          "8,7": {
            "size": [
              1,
              1
            ],
            "content": {
              "_type": "Text View",
              "_source0": "network_table:///LiveWindow/Ungrouped/PowerDistribution[1]/Chan14",
              "_title": "Ungrouped/PowerDistribution[1]/Chan14"
            }
          },
          "9,7": {
            "size": [
              1,
              1
            ],
            "content": {
              "_type": "Text View",
              "_source0": "network_table:///LiveWindow/Ungrouped/PowerDistribution[1]/Chan15",
              "_title": "Ungrouped/PowerDistribution[1]/Chan15"
            }
          },
          "10,7": {
            "size": [
              1,
              1
            ],
            "content": {
              "_type": "Text View",
              "_source0": "network_table:///LiveWindow/Ungrouped/PowerDistribution[1]/Chan16",
              "_title": "Ungrouped/PowerDistribution[1]/Chan16"
            }
          },
          "11,7": {
            "size": [
              1,
              1
            ],
            "content": {
              "_type": "Text View",
              "_source0": "network_table:///LiveWindow/Ungrouped/PowerDistribution[1]/Chan17",
              "_title": "Ungrouped/PowerDistribution[1]/Chan17"
            }
          },
          "12,7": {
            "size": [
              1,
              1
            ],
            "content": {
              "_type": "Text View",
              "_source0": "network_table:///LiveWindow/Ungrouped/PowerDistribution[1]/Chan18",
              "_title": "Ungrouped/PowerDistribution[1]/Chan18"
            }
          }
        }
      }
    },
    {
      "title": "DriveTest",
      "autoPopulate": false,
      "autoPopulatePrefix": "",
      "widgetPane": {
        "gridSize": 128.0,
        "showGrid": true,
        "hgap": 16.0,
        "vgap": 16.0,
        "titleType": 0,
        "tiles": {
          "3,0": {
            "size": [
              3,
              3
            ],
            "content": {
              "_type": "List Layout",
              "_title": "Drive Train",
              "Layout/Label position": "LEFT",
              "_children": [
                {
                  "_type": "Command",
                  "_source0": "network_table:///SmartDashboard/DriveForward",
                  "_title": "Drive Forward"
                },
                {
                  "_type": "Command",
                  "_source0": "network_table:///SmartDashboard/DriveBackward",
                  "_title": "Drive Backward"
                }
              ]
            }
          }
        }
      }
    },
    {
      "title": "Debug",
      "autoPopulate": false,
      "autoPopulatePrefix": "",
      "widgetPane": {
        "gridSize": 128.0,
        "showGrid": true,
        "hgap": 16.0,
        "vgap": 16.0,
        "titleType": 0,
        "tiles": {
          "4,0": {
            "size": [
              1,
              1
            ],
            "content": {
              "_type": "Command",
              "_source0": "network_table:///SmartDashboard/Clear Sticky Faults",
              "_title": "Clear Sticky Faults"
            }
          },
          "3,0": {
            "size": [
              1,
              1
            ],
            "content": {
              "_type": "Boolean Box",
              "_source0": "network_table:///SmartDashboard/problemExists",
              "_title": "Problem Exists",
              "Colors/Color when true": "#FF0000FF",
              "Colors/Color when false": "#008000FF"
            }
          },
          "5,0": {
            "size": [
              5,
              1
            ],
            "content": {
              "_type": "Text View",
              "_source0": "network_table:///SmartDashboard/problemSubsystem",
              "_title": "ProblemSubsystem"
            }
          }
        }
      }
    }
  ],
  "windowGeometry": {
    "x": -8.0,
    "y": -8.0,
    "width": 1936.0,
    "height": 1056.0
  }
}